forevernotes/__init__.py
forevernotes/config/db/schema.sql
forevernotes/utils/__init__.py
forevernotes/utils/db.py
forevernotes/utils/notes.py
forevernotes/utils/tags.py
forevernotes-0.0.1.dist-info/METADATA
forevernotes-0.0.1.dist-info/WHEEL
forevernotes-0.0.1.dist-info/entry_points.txt
forevernotes-0.0.1.dist-info/RECORD
